magiccluster/__init__.py
magiccluster/base.py
magiccluster/cli.py
magiccluster/clustering.py
magiccluster/magic_clustering.py
magiccluster/main.py
magiccluster/utils.py
magiccluster-0.0.3.dist-info/LICENSE
magiccluster-0.0.3.dist-info/METADATA
magiccluster-0.0.3.dist-info/WHEEL
magiccluster-0.0.3.dist-info/entry_points.txt
magiccluster-0.0.3.dist-info/top_level.txt
magiccluster-0.0.3.dist-info/RECORD
