Metadata-Version: 2.1
Name: magiccluster
Version: 0.0.3
Summary: Multi-scale semi-supervised clustering
Home-page: https://github.com/anbai106/MAGIC
Author: junhao.wen
Author-email: junhao.wen89@email.com
License: UNKNOWN
Platform: UNKNOWN
Classifier: Programming Language :: Python :: 3
Classifier: License :: OSI Approved :: MIT License
Classifier: Operating System :: OS Independent
License-File: LICENSE
